qstock/LICENSE
qstock/README.md
qstock/__init__.py
qstock/backtest/__init__.py
qstock/backtest/bt_backtest.py
qstock/backtest/turtle.py
qstock/backtest/vec_backtest.py
qstock/data/__init__.py
qstock/data/cookies.json
qstock/data/demjson.py
qstock/data/fundamental.py
qstock/data/hexin.js
qstock/data/industry.py
qstock/data/macro.py
qstock/data/money.py
qstock/data/news.py
qstock/data/ths.js
qstock/data/trade.py
qstock/data/util.py
qstock/data/wencai.py
qstock/plot/__init__.py
qstock/plot/chart_plot.py
qstock/plot/data_plot.py
qstock/stock/__init__.py
qstock/stock/stock_pool.py
qstock/stock/ths_em_pool.py
qstock-1.3.8.dist-info/METADATA
qstock-1.3.8.dist-info/WHEEL
qstock-1.3.8.dist-info/top_level.txt
qstock-1.3.8.dist-info/RECORD
