Metadata-Version: 2.1
Name: qstock
Version: 1.3.8
Summary: Quantitative finance and stock analysis using Python
Home-page: https://github.com/tkfy920/qstock
Author: Jinyi Zhang
Author-email: 723195276@qq.com
License: MIT Licence
Keywords: pip,qstock
Platform: any
Requires-Dist: numpy
Requires-Dist: pandas
Requires-Dist: matplotlib
Requires-Dist: pyecharts
Requires-Dist: tqdm
Requires-Dist: jieba
Requires-Dist: seaborn
Requires-Dist: plotly-express
Requires-Dist: beautifulsoup4
Requires-Dist: jsonpath
Requires-Dist: multitasking
Requires-Dist: plotly
Requires-Dist: py-mini-racer
Requires-Dist: requests
Requires-Dist: PyExecJS
Requires-Dist: func-timeout
Requires-Dist: pywencai
